Workbook

Sheet Synthèse
A1: SYNTHÈSE BUDGÉTAIRE — Monique Festival
A3: Catégorie | B3: Recettes prévues | C3: Recettes réelles | D3: Écart recettes | E3: Dépenses prévues | F3: Dépenses réelles | G3: Écart dépenses | H3: Marge prévue | I3: Marge réelle | J3: Écart marge
A4: Crowdfunding | B4: =Crowdfunding!C16 -> 8000 | C4: =Crowdfunding!D16 -> 0 | D4: =C4-B4 -> -8000 | E4: 0 | F4: 0 | G4: =F4-E4 -> 0 | H4: =B4-E4 -> 8000 | I4: =C4-F4 -> 0 | J4: =I4-H4 -> -8000
A5: Billetterie + Artistes | B5: =Billetterie!D10 -> 22650 | C5: =Billetterie!F10 -> 0 | D5: =C5-B5 -> -22650 | E5: =Artistes!F37+Artistes!H37 -> 21100 | F5: =Artistes!J37+Artistes!K37 -> 0 | G5: =F5-E5 -> -21100 | H5: =B5-E5 -> 1550 | I5: =C5-F5 -> 0 | J5: =I5-H5 -> -1550
A6: F&B (Buvettes + Restauration) | B6: ='F&B'!D13 -> 32442 | C6: ='F&B'!E13 -> 0 | D6: =C6-B6 -> -32442 | E6: ='F&B'!D27 -> 7925 | F6: ='F&B'!E27 -> 0 | G6: =F6-E6 -> -7925 | H6: =B6-E6 -> 24517 | I6: =C6-F6 -> 0 | J6: =I6-H6 -> -24517
A7: Ateliers (recettes + coûts ateliers) | B7: =Ateliers!D14 -> 3390 | C7: =Ateliers!E14 -> 0 | D7: =C7-B7 -> -3390 | E7: =Ateliers!D27 -> 1200 | F7: =Ateliers!E27 -> 0 | G7: =F7-E7 -> -1200 | H7: =B7-E7 -> 2190 | I7: =C7-F7 -> 0 | J7: =I7-H7 -> -2190
A8: Logistique | B8: 0 | C8: 0 | D8: =C8-B8 -> 0 | E8: =Logistique!C18 -> 15000 | F8: =Logistique!D18 -> 0 | G8: =F8-E8 -> -15000 | H8: =B8-E8 -> -15000 | I8: =C8-F8 -> 0 | J8: =I8-H8 -> 15000
A9: Frais divers | B9: ='Frais divers'!D12 -> 0 | C9: ='Frais divers'!E12 -> 0 | D9: =C9-B9 -> 0 | E9: ='Frais divers'!D29 -> 6420 | F9: ='Frais divers'!E29 -> 0 | G9: =F9-E9 -> -6420 | H9: =B9-E9 -> -6420 | I9: =C9-F9 -> 0 | J9: =I9-H9 -> 6420
A11: Ajustement défraiement artistes (-25%) | E11: -1650
A12: TOTAL | B12: =SUM(B4:B11) -> 66482 | C12: =SUM(C4:C11) -> 0 | D12: =SUM(D4:D11) -> -66482 | E12: =SUM(E4:E11) -> 49995 | F12: =SUM(F4:F11) -> 0 | G12: =SUM(G4:G11) -> -51645 | H12: =SUM(H4:H11) -> 14837 | I12: =SUM(I4:I11) -> 0 | J12: =SUM(J4:J11) -> -14837
A15: SCÉNARIOS PAR JAUGE
A17: Scénario | B17: Recettes | C17: Coûts | D17: Marge | E17: Jauge | F17: Nb festivaliers
A18: Jauge -20% | B18: 47464 | C18: 47767 | D18: -303 | E18: 960 | F18: 960
A19: Jauge standard | B19: 58482 | C19: 49907 | D19: 8575 | E19: 1 200 | F19: 1200
A20: Jauge +20% | B20: 69500 | C20: 52048 | D20: 17453 | E20: 1 440 | F20: 1440

Sheet Crowdfunding
A1: CROWDFUNDING — Recettes HelloAsso
A3: Date | B3: Description | C3: Prévu | D3: Réel | E3: Écart
B4: Objectif crowdfunding (palier 3) | C4: 8000 | E4: =D4-C4 -> -8000
E5: =D5-C5 -> 0
E6: =D6-C6 -> 0
E7: =D7-C7 -> 0
E8: =D8-C8 -> 0
E9: =D9-C9 -> 0
E10: =D10-C10 -> 0
E11: =D11-C11 -> 0
E12: =D12-C12 -> 0
E13: =D13-C13 -> 0
E14: =D14-C14 -> 0
A16: TOTAL CROWDFUNDING | C16: =SUM(C4:C14) -> 8000 | D16: =SUM(D4:D14) -> 0 | E16: =SUM(E4:E14) -> -8000

Sheet Billetterie
A1: BILLETTERIE — Recettes
A3: Type | B3: Tarif | C3: Nb prévu | D3: Recettes prévues | E3: Nb réel | F3: Recettes réelles | G3: Écart
A4: Early bird pass 3 jours | B4: 20 | C4: 120 | D4: =B4*C4 -> 2400 | F4: =B4*E4 -> 0 | G4: =F4-D4 -> -2400
A5: Pass 3 jours | B5: 25 | C5: 480 | D5: =B5*C5 -> 12000 | F5: =B5*E5 -> 0 | G5: =F5-D5 -> -12000
A6: Vendredi | B6: 10 | C6: 150 | D6: =B6*C6 -> 1500 | F6: =B6*E6 -> 0 | G6: =F6-D6 -> -1500
A7: Samedi | B7: 15 | C7: 300 | D7: =B7*C7 -> 4500 | F7: =B7*E7 -> 0 | G7: =F7-D7 -> -4500
A8: Dimanche | B8: 15 | C8: 150 | D8: =B8*C8 -> 2250 | F8: =B8*E8 -> 0 | G8: =F8-D8 -> -2250
A10: TOTAL BILLETTERIE | C10: =SUM(C4:C8) -> 1200 | D10: =SUM(D4:D8) -> 22650 | E10: =SUM(E4:E8) -> 0 | F10: =SUM(F4:F8) -> 0 | G10: =SUM(G4:G8) -> -22650

Sheet F&B
A1: F&B — Buvettes + Restauration
A3: Recettes
A5: Date | B5: Description | C5: Type | D5: Prévu | E5: Réel | F5: Écart
B6: Buvette — Vendredi | C6: Recette | D6: 4238 | F6: =E6-D6 -> -4238
B7: Buvette — Samedi | C7: Recette | D7: 12244 | F7: =E7-D7 -> -12244
B8: Buvette — Dimanche | C8: Recette | D8: 4238 | F8: =E8-D8 -> -4238
B9: Restauration — Vendredi | C9: Recette | D9: 2398 | F9: =E9-D9 -> -2398
B10: Restauration — Samedi | C10: Recette | D10: 6926 | F10: =E10-D10 -> -6926
B11: Restauration — Dimanche | C11: Recette | D11: 2398 | F11: =E11-D11 -> -2398
A13: TOTAL RECETTES F&B | D13: =SUM(D6:D11) -> 32442 | E13: =SUM(E6:E11) -> 0 | F13: =SUM(F6:F11) -> -32442
A15: Dépenses
A17: Date | B17: Description | C17: Type | D17: Prévu | E17: Réel | F17: Écart
B18: Achats buvette (bières, softs, vins…) | C18: Dépense | D18: 4440 | F18: =E18-D18 -> -4440
B19: Achats restauration (matières premières) | C19: Dépense | D19: 2930 | F19: =E19-D19 -> -2930
B20: Restauration artistes (prix coûtant) | C20: Dépense | D20: 555 | F20: =E20-D20 -> -555
F21: =E21-D21 -> 0
F22: =E22-D22 -> 0
F23: =E23-D23 -> 0
F24: =E24-D24 -> 0
F25: =E25-D25 -> 0
A27: TOTAL DÉPENSES F&B | D27: =SUM(D18:D25) -> 7925 | E27: =SUM(E18:E25) -> 0 | F27: =SUM(F18:F25) -> -7925

Sheet Ateliers
A1: ATELIERS — Recettes & Dépenses
A3: Recettes (cotisations participants)
A5: Date | B5: Description | C5: Type | D5: Prévu | E5: Réel | F5: Écart
B6: Masterclass chant lyrique (4 élèves × 60 €) | C6: Recette | D6: 240 | F6: =E6-D6 -> -240
B7: Atelier écriture (15 pers × 50 € + 150 € lycée) | C7: Recette | D7: 900 | F7: =E7-D7 -> -900
B8: Atelier musique & théâtre (30 pers × 50 €) | C8: Recette | D8: 1500 | F8: =E8-D8 -> -1500
B9: Atelier DJ (15 pers × 50 €) | C9: Recette | D9: 750 | F9: =E9-D9 -> -750
F10: =E10-D10 -> 0
F11: =E11-D11 -> 0
F12: =E12-D12 -> 0
A14: TOTAL RECETTES ATELIERS | D14: =SUM(D6:D12) -> 3390 | E14: =SUM(E6:E12) -> 0 | F14: =SUM(F6:F12) -> -3390
A16: Dépenses (intervenants ateliers)
A18: Date | B18: Description | C18: Type | D18: Prévu | E18: Réel | F18: Écart
B19: Rép. Fabulo (4 art. x 2 jours x 100€) | C19: Dépense | D19: 800 | F19: =E19-D19 -> -800
B20: Rép. Masterclass chant — Romane (incl. Fabulo) | C20: Dépense | D20: 0 | F20: =E20-D20 -> 0
B21: Rép. Atelier écriture — Sylvain (2 jours x 100€) | C21: Dépense | D21: 200 | F21: =E21-D21 -> -200
B22: Rép. Atelier DJ — Jeff (2 jours x 100€) | C22: Dépense | D22: 200 | F22: =E22-D22 -> -200
F23: =E23-D23 -> 0
F24: =E24-D24 -> 0
F25: =E25-D25 -> 0
A27: TOTAL DÉPENSES ATELIERS | D27: =SUM(D19:D25) -> 1200 | E27: =SUM(E19:E25) -> 0 | F27: =SUM(F19:F25) -> -1200

Sheet Artistes
A1: ARTISTES — Dépenses (cachet 250€, rép. 100€, défr. 200€ max)
A3: Nom | B3: Catégorie | C3: Atelier | D3: Nb cachets | E3: Nb rép. | F3: Coût cachets prévu | G3: Coût rép. prévu | H3: Défraiement prévu | I3: Total prévu | J3: Paiement réel | K3: Défraiement réel | L3: Total réel | M3: Date paiement | N3: Écart
A4: George Cabaret | B4: Musique | D4: 1 | E4: 0 | F4: 250 | G4: 0 | H4: 200 | I4: =F4+G4+H4 -> 450 | L4: =J4+K4 -> 0 | N4: =L4-I4 -> -450
A5: Loretta | B5: Musique | D5: 1 | E5: 0 | F5: 250 | G5: 0 | H5: 200 | I5: =F5+G5+H5 -> 450 | L5: =J5+K5 -> 0 | N5: =L5-I5 -> -450
A6: ? (Ven 19h30) | B6: Musique | D6: 1 | E6: 0 | F6: 250 | G6: 0 | H6: 200 | I6: =F6+G6+H6 -> 450 | L6: =J6+K6 -> 0 | N6: =L6-I6 -> -450
A7: Manu (Wambo) | B7: Musique | D7: 1 | E7: 0 | F7: 250 | G7: 0 | H7: 200 | I7: =F7+G7+H7 -> 450 | L7: =J7+K7 -> 0 | N7: =L7-I7 -> -450
A8: Jeff The Fool | B8: Musique | C8: Atelier DJ | D8: 0 | E8: 2 | F8: 0 | G8: 200 | H8: 200 | I8: =F8+G8+H8 -> 400 | L8: =J8+K8 -> 0 | N8: =L8-I8 -> -400
A9: Wet Enough (5 art.) | B9: Musique — Coll | D9: 5 | E9: 0 | F9: 1250 | G9: 0 | H9: 1000 | I9: =F9+G9+H9 -> 2250 | L9: =J9+K9 -> 0 | N9: =L9-I9 -> -2250
A10: Osmosis (3 art.) | B10: Musique — Coll | D10: 3 | E10: 0 | F10: 750 | G10: 0 | H10: 600 | I10: =F10+G10+H10 -> 1350 | L10: =J10+K10 -> 0 | N10: =L10-I10 -> -1350
A11: Léopold (famille) | B11: Musique | C11: Atelier DJ | D11: 0 | E11: 2 | F11: 0 | G11: 0 | H11: 0 | I11: =F11+G11+H11 -> 0 | L11: =J11+K11 -> 0 | N11: =L11-I11 -> 0
A12: Luther (famille) | B12: Musique | D12: 0 | E12: 0 | F12: 0 | G12: 0 | H12: 0 | I12: =F12+G12+H12 -> 0 | L12: =J12+K12 -> 0 | N12: =L12-I12 -> 0
A13: Marius (Fabulo) | B13: Fabulo — Coll | C13: Musique & théâtre | D13: 2 | E13: 2 | F13: 500 | G13: 200 | H13: 200 | I13: =F13+G13+H13 -> 900 | L13: =J13+K13 -> 0 | N13: =L13-I13 -> -900
A14: Maya (Fabulo) | B14: Fabulo — Coll | C14: Musique & théâtre | D14: 2 | E14: 2 | F14: 500 | G14: 200 | H14: 200 | I14: =F14+G14+H14 -> 900 | L14: =J14+K14 -> 0 | N14: =L14-I14 -> -900
A15: Raphaëlle (Fabulo) | B15: Fabulo — Coll | C15: Musique & théâtre | D15: 2 | E15: 2 | F15: 500 | G15: 200 | H15: 200 | I15: =F15+G15+H15 -> 900 | L15: =J15+K15 -> 0 | N15: =L15-I15 -> -900
A16: Romane Cabaret | B16: Fabulo — Coll | C16: Masterclass chant | D16: 4 | E16: 2 | F16: 1000 | G16: 200 | H16: 200 | I16: =F16+G16+H16 -> 1400 | L16: =J16+K16 -> 0 | N16: =L16-I16 -> -1400
A17: Lorraine (famille) | B17: Fabulo | C17: Musique & théâtre | D17: 0 | E17: 0 | F17: 0 | G17: 0 | H17: 0 | I17: =F17+G17+H17 -> 0 | L17: =J17+K17 -> 0 | N17: =L17-I17 -> 0
A18: Violoncelliste 1 (Marc T.) | B18: Classique | D18: 2 | E18: 0 | F18: 500 | G18: 0 | H18: 200 | I18: =F18+G18+H18 -> 700 | L18: =J18+K18 -> 0 | N18: =L18-I18 -> -700
A19: Violoncelliste 2 | B19: Classique | D19: 2 | E19: 0 | F19: 500 | G19: 0 | H19: 200 | I19: =F19+G19+H19 -> 700 | L19: =J19+K19 -> 0 | N19: =L19-I19 -> -700
A20: Violoncelliste 3 | B20: Classique | D20: 2 | E20: 0 | F20: 500 | G20: 0 | H20: 200 | I20: =F20+G20+H20 -> 700 | L20: =J20+K20 -> 0 | N20: =L20-I20 -> -700
A21: Violoncelliste 4 | B21: Classique | D21: 2 | E21: 0 | F21: 500 | G21: 0 | H21: 200 | I21: =F21+G21+H21 -> 700 | L21: =J21+K21 -> 0 | N21: =L21-I21 -> -700
A22: Volodia Van Keulen | B22: Classique | D22: 2 | E22: 0 | F22: 500 | G22: 0 | H22: 200 | I22: =F22+G22+H22 -> 700 | L22: =J22+K22 -> 0 | N22: =L22-I22 -> -700
A23: Pianiste (Augustin) | B23: Classique | D23: 1 | E23: 0 | F23: 250 | G23: 0 | H23: 200 | I23: =F23+G23+H23 -> 450 | L23: =J23+K23 -> 0 | N23: =L23-I23 -> -450
A24: Sylvain Septours | B24: Théâtre | C24: Atelier écriture | D24: 0 | E24: 2 | F24: 0 | G24: 200 | H24: 200 | I24: =F24+G24+H24 -> 400 | L24: =J24+K24 -> 0 | N24: =L24-I24 -> -400
A25: Comédien 1 (Treize Clique) | B25: Théâtre — Coll | D25: 1 | E25: 0 | F25: 250 | G25: 0 | H25: 200 | I25: =F25+G25+H25 -> 450 | L25: =J25+K25 -> 0 | N25: =L25-I25 -> -450
A26: Comédien 2 (Treize Clique) | B26: Théâtre — Coll | D26: 1 | E26: 0 | F26: 250 | G26: 0 | H26: 200 | I26: =F26+G26+H26 -> 450 | L26: =J26+K26 -> 0 | N26: =L26-I26 -> -450
A27: Comédien 3 (Treize Clique) | B27: Théâtre — Coll | D27: 1 | E27: 0 | F27: 250 | G27: 0 | H27: 200 | I27: =F27+G27+H27 -> 450 | L27: =J27+K27 -> 0 | N27: =L27-I27 -> -450
A28: Lewis (famille) | B28: Théâtre | C28: Éloquence | D28: 0 | E28: 0 | F28: 0 | G28: 0 | H28: 0 | I28: =F28+G28+H28 -> 0 | L28: =J28+K28 -> 0 | N28: =L28-I28 -> 0
A29: Cie théâtre 1 (4 art.) | B29: Théâtre — AP | D29: 4 | E29: 0 | F29: 1000 | G29: 0 | H29: 0 | I29: =F29+G29+H29 -> 1000 | L29: =J29+K29 -> 0 | N29: =L29-I29 -> -1000
A30: Cie théâtre 2 (4 art.) | B30: Théâtre — AP | D30: 4 | E30: 0 | F30: 1000 | G30: 0 | H30: 0 | I30: =F30+G30+H30 -> 1000 | L30: =J30+K30 -> 0 | N30: =L30-I30 -> -1000
A31: Cie théâtre 3 (4 art.) | B31: Théâtre — AP | D31: 4 | E31: 0 | F31: 1000 | G31: 0 | H31: 0 | I31: =F31+G31+H31 -> 1000 | L31: =J31+K31 -> 0 | N31: =L31-I31 -> -1000
A32: Cie théâtre 4 (4 art.) | B32: Théâtre — AP | D32: 4 | E32: 0 | F32: 1000 | G32: 0 | H32: 0 | I32: =F32+G32+H32 -> 1000 | L32: =J32+K32 -> 0 | N32: =L32-I32 -> -1000
A33: Fenêtres des heures (2 art.) | B33: Nouveau | D33: 2 | E33: 0 | F33: 500 | G33: 0 | H33: 400 | I33: =F33+G33+H33 -> 900 | L33: =J33+K33 -> 0 | N33: =L33-I33 -> -900
A34: Fannelie | B34: Nouveau | D34: 1 | E34: 0 | F34: 250 | G34: 0 | H34: 200 | I34: =F34+G34+H34 -> 450 | L34: =J34+K34 -> 0 | N34: =L34-I34 -> -450
A35: Karina Ziegler (3 art.) | B35: Nouveau — Coll | D35: 3 | E35: 0 | F35: 750 | G35: 0 | H35: 600 | I35: =F35+G35+H35 -> 1350 | L35: =J35+K35 -> 0 | N35: =L35-I35 -> -1350
A37: TOTAL ARTISTES | D37: =SUM(D4:D36) -> 58 | E37: =SUM(E4:E36) -> 14 | F37: =SUM(F4:F35) -> 14500 | G37: =SUM(G4:G35) -> 1200 | H37: =SUM(H4:H35) -> 6600 | I37: =SUM(I4:I35) -> 22300 | J37: =SUM(J4:J35) -> 0 | K37: =SUM(K4:K35) -> 0 | L37: =SUM(L4:L35) -> 0 | N37: =SUM(N4:N35) -> -22300

Sheet Logistique
A1: LOGISTIQUE — Dépenses
A3: Date | B3: Description | C3: Prévu | D3: Réel | E3: Écart
B4: Location salle / terrain | C4: 3000 | E4: =D4-C4 -> -3000
B5: Sonorisation | C5: 3000 | E5: =D5-C5 -> -3000
B6: Éclairage / lumière | C6: 2000 | E6: =D6-C6 -> -2000
B7: Scène / podium | C7: 2000 | E7: =D7-C7 -> -2000
B8: Toilettes / sanitaires | C8: 1500 | E8: =D8-C8 -> -1500
B9: Électricité / groupe électrogène | C9: 1500 | E9: =D9-C9 -> -1500
B10: Barrières / sécurité | C10: 1000 | E10: =D10-C10 -> -1000
B11: Mobilier (tables, chaises, tentes) | C11: 1000 | E11: =D11-C11 -> -1000
E12: =D12-C12 -> 0
E13: =D13-C13 -> 0
E14: =D14-C14 -> 0
E15: =D15-C15 -> 0
E16: =D16-C16 -> 0
A18: TOTAL LOGISTIQUE | C18: =SUM(C4:C16) -> 15000 | D18: =SUM(D4:D16) -> 0 | E18: =SUM(E4:E16) -> -15000

Sheet Frais divers
A1: FRAIS DIVERS — Recettes & Dépenses
A3: Recettes (subventions, dons, sponsors)
A5: Date | B5: Description | C5: Type | D5: Prévu | E5: Réel | F5: Écart
F6: =E6-D6 -> 0
F7: =E7-D7 -> 0
F8: =E8-D8 -> 0
F9: =E9-D9 -> 0
F10: =E10-D10 -> 0
A12: TOTAL RECETTES DIVERS | D12: =SUM(D6:D10) -> 0 | E12: =SUM(E6:E10) -> 0 | F12: =SUM(F6:F10) -> 0
A14: Dépenses (SACEM, communication, assurance, admin, imprévus)
A16: Date | B16: Description | C16: Type | D16: Prévu | E16: Réel | F16: Écart
B17: SACEM Billetterie (8,8%) | C17: Dépense | D17: 1993 | F17: =E17-D17 -> -1993
B18: SACEM Restauration/Buvettes (4,4%) | C18: Dépense | D18: 1427 | F18: =E18-D18 -> -1427
B19: Assurance événement | C19: Dépense | D19: 1000 | F19: =E19-D19 -> -1000
B20: Communication (affiches, flyers, vidéo) | C20: Dépense | D20: 1000 | F20: =E20-D20 -> -1000
B21: Frais administratifs | C21: Dépense | D21: 500 | F21: =E21-D21 -> -500
B22: Imprévus | C22: Dépense | D22: 500 | F22: =E22-D22 -> -500
F23: =E23-D23 -> 0
F24: =E24-D24 -> 0
F25: =E25-D25 -> 0
F26: =E26-D26 -> 0
F27: =E27-D27 -> 0
A29: TOTAL DÉPENSES DIVERS | D29: =SUM(D17:D27) -> 6420 | E29: =SUM(E17:E27) -> 0 | F29: =SUM(F17:F27) -> -6420

Sheet Trésorerie
A1: TRÉSORERIE — Flux par date
A3: Solde initial | D3: 0 | F3: 0
A4: Date | B4: Catégorie | C4: Description | D4: Entrée | E4: Sortie | F4: Solde cumulé
F5: =F3+D5-E5 -> 0
F6: =F5+D6-E6 -> 0
F7: =F6+D7-E7 -> 0
F8: =F7+D8-E8 -> 0
F9: =F8+D9-E9 -> 0
F10: =F9+D10-E10 -> 0
F11: =F10+D11-E11 -> 0
F12: =F11+D12-E12 -> 0
F13: =F12+D13-E13 -> 0
F14: =F13+D14-E14 -> 0
F15: =F14+D15-E15 -> 0
F16: =F15+D16-E16 -> 0
F17: =F16+D17-E17 -> 0
... F34: =F33+D34-E34 -> 0
A36: TOTAUX | D36: =SUM(D5:D34) -> 0 | E36: =SUM(E5:E34) -> 0 | F36: =F34 -> 0
